Metadata-Version: 2.1
Name: pr_colored
Version: 1.5.2
Summary: colored print() as pr()
Author: Andrew M
Author-email: toni25010@gmail.com
License: MIT
Requires-Dist: termcolor
